LICENCE.txt
MANIFEST.in
README.rst
setup.cfg
setup.py
emencia_jinja_secretkey.egg-info/PKG-INFO
emencia_jinja_secretkey.egg-info/SOURCES.txt
emencia_jinja_secretkey.egg-info/dependency_links.txt
emencia_jinja_secretkey.egg-info/requires.txt
emencia_jinja_secretkey.egg-info/top_level.txt
emencia_jinja_secretkey.egg-info/zip-safe
jinja_secretkey/__init__.py
jinja_secretkey/secret_key.py